pyquickmaps/pqm.py
pyquickmaps-0.2.0.dist-info/LICENSE
pyquickmaps-0.2.0.dist-info/METADATA
pyquickmaps-0.2.0.dist-info/WHEEL
pyquickmaps-0.2.0.dist-info/top_level.txt
pyquickmaps-0.2.0.dist-info/RECORD
